NWS/NWS.py
NWS/__init__.py
NWS-1.3.dist-info/METADATA
NWS-1.3.dist-info/WHEEL
NWS-1.3.dist-info/top_level.txt
NWS-1.3.dist-info/RECORD
